README.md
setup.py
numpyp/.env
numpyp/__init__.py
numpyp/code.py
numpyp/code_t.py
numpyp/see.py
numpyp/telegram_handler.py
numpyp.egg-info/PKG-INFO
numpyp.egg-info/SOURCES.txt
numpyp.egg-info/dependency_links.txt
numpyp.egg-info/requires.txt
numpyp.egg-info/top_level.txt
numpyp/theory/__init__.py